<?xml version="1.0" encoding="UTF-8"?>
<objects serializationModel="Studio.01.10.00">
    <object class="AudioFile" id="{ae1a1314-2481-4068-b4a3-0b883017bf01}">
        <property name="assetPath">
            <value>Klaxon/Klaxon1.wav</value>
        </property>
        <property name="frequencyInKHz">
            <value>44.0999985</value>
        </property>
        <property name="channelCount">
            <value>2</value>
        </property>
        <property name="length">
            <value>3.8082539682539682</value>
        </property>
        <relationship name="masterAssetFolder">
            <destination>{91fc85e5-cd8c-450c-baa4-736099ee1b54}</destination>
        </relationship>
    </object>
</objects>
